ludax/__init__.py
ludax/config.py
ludax/environment.py
ludax/game_info.py
ludax/game_parser.py
ludax/grammar.lark
ludax/struct.py
ludax/utils.py
ludax/games/__init__.py
ludax/games/complexity_demo.ldx
ludax/games/connect_four.ldx
ludax/games/connect_six.ldx
ludax/games/gomoku.ldx
ludax/games/hex.ldx
ludax/games/pente.ldx
ludax/games/reversi.ldx
ludax/games/tic_tac_toe.ldx
ludax/games/yavalath.ldx
ludax/games/yavalax.ldx
ludax/gui/__init__.py
ludax/gui/render.py
ludax/gui/routes.py
ludax/gui/static/main.css
ludax/gui/templates/game.html
ludax/gui/templates/index.html
ludax-0.0.7.dist-info/licenses/LICENSE
ludax-0.0.7.dist-info/METADATA
ludax-0.0.7.dist-info/WHEEL
ludax-0.0.7.dist-info/top_level.txt
ludax-0.0.7.dist-info/RECORD
