Metadata-Version: 2.4
Name: ludax
Version: 0.0.7
Summary: Ludax is a domain-specific language for board games that automatically compiles into hardware-accelerated learning environments with the JAX library
Author-email: Graham Todd <gdrtodd@gmail.com>, Alexander Padula <alexpadula2001@gmail.com>
License-Expression: Apache-2.0
Project-URL: Homepage, https://github.com/gdrtodd/ludax
Project-URL: Issues, https://github.com/gdrtodd/ludax/issues
Classifier: Programming Language :: Python :: 3
Classifier: Operating System :: OS Independent
Requires-Python: >=3.9
License-File: LICENSE
Requires-Dist: jax
Requires-Dist: lark
Requires-Dist: flax
Provides-Extra: gui
Requires-Dist: flask; extra == "gui"
Requires-Dist: svgwrite; extra == "gui"
Dynamic: license-file
